pynwfd/__init__.py
pynwfd/grib_write.py
pynwfd/lib64/libNwfd-grib2.so
pynwfd/lib64/libpng16.dll
pynwfd/lib64/msvcp120.dll
pynwfd/lib64/msvcr120.dll
pynwfd/lib64/nwfd-grib2-win64.dll
pynwfd/lib64/zlib1.dll
pynwfd-0.0.1.dist-info/METADATA
pynwfd-0.0.1.dist-info/WHEEL
pynwfd-0.0.1.dist-info/licenses/LICENSE
pynwfd-0.0.1.dist-info/RECORD
