Metadata-Version: 2.1
Name: pynwfd
Version: 0.0.1
Summary: a python API for cma nwfd-grib2 c/c++ api
Author-email: Qi dapeng <dpqnju@126.com>
License: copyright for CMA. MIT license.
License-File: LICENSE
Classifier: License :: OSI Approved :: MIT License
Classifier: Operating System :: OS Independent
Classifier: Programming Language :: Python :: 3
Requires-Python: >=3.0
